geomapclip/__init__.py
geomapclip/setup.py
geomapclip/images/Kauai.png
geomapclip/model/GeoMapCLIP.py
geomapclip/model/__init__.py
geomapclip/model/image_encoder.py
geomapclip/model/location_encoder.py
geomapclip/model/misc.py
geomapclip/model/gps_gallery/coordinates_100K.csv
geomapclip/model/gps_gallery/coordinates_400K.csv
geomapclip/model/gps_gallery/fibonacci_lattice_land.csv
geomapclip/model/rff/__init__.py
geomapclip/model/rff/functional.py
geomapclip/model/rff/layers.py
geomapclip/model/weights/image_encoder_mlp_weights.pth
geomapclip/model/weights/location_encoder_weights.pth
geomapclip/model/weights/logit_scale_weights.pth
geomapclip/train/__init__.py
geomapclip/train/dataloader.py
geomapclip/train/eval.py
geomapclip/train/train.py
geomapclip-0.0.3.dist-info/LICENSE
geomapclip-0.0.3.dist-info/METADATA
geomapclip-0.0.3.dist-info/WHEEL
geomapclip-0.0.3.dist-info/top_level.txt
geomapclip-0.0.3.dist-info/RECORD
