Metadata-Version: 2.1
Name: geomapclip
Version: 0.0.3
Home-page: https://github.com/junghawoo/geomap-clip
Author: Jungha Woo
Author-email: wooj@purdue.edu
License: MIT
Classifier: Programming Language :: Python :: 3
Classifier: License :: OSI Approved :: MIT License
Classifier: Operating System :: OS Independent
Requires-Python: >=3.6
License-File: LICENSE
Requires-Dist: torch
Requires-Dist: torchvision
Requires-Dist: Pillow
Requires-Dist: transformers
Requires-Dist: pandas
Requires-Dist: numpy
Requires-Dist: geopy
